[
  {
    "id": "1",
    "name": "calculator-js",
    "description": "A simple calculator",
    "screenshots": ["./data/calculator1.PNG", "./data/calculator2.PNG"],
    "github": "https://github.com/sami-29/calculator-js"
  },
  {
    "id": "2",
    "name": "chess-js",
    "description": "A chess game",
    "screenshots": [
      "./data/chess1.PNG",
      "./data/chess2.PNG",
      "./data/chess3.PNG"
    ],
    "github": "https://github.com/sami-29/chess-js"
  },
  {
    "id": "3",
    "name": "snake-js",
    "description": "A snake game",
    "screenshots": ["./data/snake1.PNG"],
    "github": "https://github.com/sami-29/snake-js"
  },
  {
    "id": "4",
    "name": "facebook-clone-react",
    "description": "A clone of facebook using react",
    "screenshots": ["./data/fb1.PNG", "./data/fb2.PNG"],
    "github": "https://github.com/sami-29/facebook-clone-react"
  },
  {
    "id": "5",
    "name": "todo-list-react",
    "description": "A todo list using react",
    "screenshots": [
      "./data/todo1.PNG",
      "./data/todo2.PNG",
      "./data/todo3.PNG",
      "./data/todo4.PNG"
    ],
    "github": "https//github.com/sami-29/todo-list-react"
  },
  {
    "id": "6",
    "name": "linus-tech-tips",
    "description": "An e-commerce website using vanilla js and php",
    "screenshots": [
      "./data/linus1.PNG",
      "./data/linus2.PNG",
      "./data/linus3.PNG",
      "./data/linus4.PNG",
      "./data/linus5.PNG",
      "./data/linus6.PNG",
      "./data/linus7.PNG"
    ],
    "github": "https//github.com/sami-29/linus-tech-tips"
  },
  {
    "id": "7",
    "name": "huddle-landing-page",
    "description": "A landing page for a startup",
    "screenshots": [
      "./data/huddle1.PNG",
      "./data/huddle2.PNG",
      "./data/huddle3.PNG"
    ],
    "github": "https//github.com/sami-29/huddle-landing-page"
  },
  {
    "id": 8,
    "name": "rock-paper-scissors-react",
    "description": "A game of rock paper scissors using react",
    "screenshots": ["./data/rps1.PNG", "./data/rps2.PNG"],
    "github": "https://github.com/sami-29/rock-paper-scissors-react"
  }
]
